{"version":"0.11","dist":"MooseX-Aliases-0.11","provides":{"MooseX::Aliases::Meta::Trait::Role::ApplicationToClass":{"file":"lib/MooseX/Aliases/Meta/Trait/Role/ApplicationToClass.pm","version":"0.11"},"MooseX::Aliases":{"version":"0.11","file":"lib/MooseX/Aliases.pm"},"MooseX::Aliases::Meta::Trait::Attribute":{"version":"0.11","file":"lib/MooseX/Aliases/Meta/Trait/Attribute.pm"},"MooseX::Aliases::Meta::Trait::Role::ApplicationToRole":{"version":"0.11","file":"lib/MooseX/Aliases/Meta/Trait/Role/ApplicationToRole.pm"},"MooseX::Aliases::Meta::Trait::Role":{"version":"0.11","file":"lib/MooseX/Aliases/Meta/Trait/Role.pm"},"MooseX::Aliases::Meta::Trait::Class":{"file":"lib/MooseX/Aliases/Meta/Trait/Class.pm","version":"0.11"},"MooseX::Aliases::Meta::Trait::Role::Composite":{"version":"0.11","file":"lib/MooseX/Aliases/Meta/Trait/Role/Composite.pm"},"MooseX::Aliases::Meta::Trait::Method":{"version":"0.11","file":"lib/MooseX/Aliases/Meta/Trait/Method.pm"}},"target":"MooseX::Aliases","name":"MooseX::Aliases","pathname":"D/DO/DOY/MooseX-Aliases-0.11.tar.gz"}