{"pathname":"G/GW/GWILLIAMS/RDF-Trine-1.014.tar.gz","dist":"RDF-Trine-1.014","version":"1.014","name":"RDF::Trine","provides":{"RDF::Trine::Error::DatabaseError":{"version":"1.014","file":"lib/RDF/Trine/Error.pm"},"RDF::Trine::Iterator":{"file":"lib/RDF/Trine/Iterator.pm","version":"1.014"},"RDF::Trine::Parser::NTriples":{"file":"lib/RDF/Trine/Parser/NTriples.pm","version":"1.014"},"RDF::Trine::Store::Redland":{"file":"lib/RDF/Trine/Store/Redland.pm","version":"1.014"},"RDF::Trine::Node::Variable":{"file":"lib/RDF/Trine/Node/Variable.pm","version":"1.014"},"RDF::Trine::Store::Redis":{"file":"lib/RDF/Trine/Store/Redis.pm","version":"1.014"},"RDF::Trine::Pattern":{"file":"lib/RDF/Trine/Pattern.pm","version":"1.014"},"RDF::Trine::Error::ParserError::Tokenized":{"version":"1.014","file":"lib/RDF/Trine/Error.pm"},"RDF::Trine::Node::Nil":{"file":"lib/RDF/Trine/Node/Nil.pm","version":"1.014"},"RDF::Trine::Error::MethodInvocationError":{"file":"lib/RDF/Trine/Error.pm","version":"1.014"},"RDF::Trine::Parser::Redland::Trig":{"version":"1.014","file":"lib/RDF/Trine/Parser/Redland.pm"},"RDF::Trine::Parser::RDFXML":{"file":"lib/RDF/Trine/Parser/RDFXML.pm","version":"1.014"},"RDF::Trine::Node::Resource":{"file":"lib/RDF/Trine/Node/Resource.pm","version":"1.014"},"RDF::Trine::Parser::Redland::RDFXML":{"file":"lib/RDF/Trine/Parser/Redland.pm","version":"1.014"},"RDF::Trine::Node":{"version":"1.014","file":"lib/RDF/Trine/Node.pm"},"RDF::Trine::Parser::Redland::Turtle":{"file":"lib/RDF/Trine/Parser/Redland.pm","version":"1.014"},"RDF::Trine::Serializer::FileSink":{"version":"1.014","file":"lib/RDF/Trine/Serializer.pm"},"RDF::Trine::Serializer::Turtle":{"version":"1.014","file":"lib/RDF/Trine/Serializer/Turtle.pm"},"RDF::Trine::Parser::Turtle::Lexer":{"file":"lib/RDF/Trine/Parser/Turtle/Lexer.pm","version":"1.014"},"RDF::Trine::Namespace":{"file":"lib/RDF/Trine/Namespace.pm","version":"1.014"},"RDF::Trine::Parser::TriG":{"version":"1.014","file":"lib/RDF/Trine/Parser/TriG.pm"},"RDF::Trine::Parser::Redland":{"file":"lib/RDF/Trine/Parser/Redland.pm","version":"1.014"},"RDF::Trine::Error::QuerySyntaxError":{"version":"1.014","file":"lib/RDF/Trine/Error.pm"},"RDF::Trine::Parser::RDFXML::SAXHandler":{"file":"lib/RDF/Trine/Parser/RDFXML.pm","version":"1.014"},"RDF::Trine::Model::Dataset":{"version":"1.014","file":"lib/RDF/Trine/Model/Dataset.pm"},"RDF::Trine::Parser::Turtle":{"version":"1.014","file":"lib/RDF/Trine/Parser/Turtle.pm"},"RDF::Trine::Serializer::NTriples::Canonical":{"version":"1.014","file":"lib/RDF/Trine/Serializer/NTriples/Canonical.pm"},"RDF::Trine::Serializer::NTriples":{"version":"1.014","file":"lib/RDF/Trine/Serializer/NTriples.pm"},"RDF::Trine::Graph":{"version":"1.014","file":"lib/RDF/Trine/Graph.pm"},"RDF::Trine::Model::Union":{"version":"1.014","file":"lib/RDF/Trine/Model/Union.pm"},"RDF::Trine::Serializer::NQuads":{"version":"1.014","file":"lib/RDF/Trine/Serializer/NQuads.pm"},"RDF::Trine::Model":{"version":"1.014","file":"lib/RDF/Trine/Model.pm"},"RDF::Trine::Store::DBI::SQLite":{"file":"lib/RDF/Trine/Store/DBI/SQLite.pm","version":"1.014"},"RDF::Trine::Store::Dydra":{"file":"lib/RDF/Trine/Store/Dydra.pm","version":"1.014"},"RDF::Trine::Store::SPARQL":{"file":"lib/RDF/Trine/Store/SPARQL.pm","version":"1.014"},"RDF::Trine::NamespaceMap":{"file":"lib/RDF/Trine/NamespaceMap.pm","version":"1.014"},"RDF::Trine::Iterator::Bindings":{"file":"lib/RDF/Trine/Iterator/Bindings.pm","version":"1.014"},"RDF::Trine::Serializer::TSV":{"file":"lib/RDF/Trine/Serializer/TSV.pm","version":"1.014"},"RDF::Trine":{"file":"lib/RDF/Trine.pm","version":"1.014"},"RDF::Trine::Serializer::RDFXML":{"version":"1.014","file":"lib/RDF/Trine/Serializer/RDFXML.pm"},"RDF::Trine::Iterator::Bindings::Materialized":{"file":"lib/RDF/Trine/Iterator/Bindings/Materialized.pm","version":"1.014"},"RDF::Trine::Error::ParserError::Explainable":{"version":"1.014","file":"lib/RDF/Trine/Error.pm"},"RDF::Trine::Parser::Turtle::Token":{"file":"lib/RDF/Trine/Parser/Turtle/Token.pm"},"RDF::Trine::Store::LanguagePreference":{"version":"1.014","file":"lib/RDF/Trine/Store/LanguagePreference.pm"},"RDF::Trine::Parser::RDFPatch":{"version":"1.014","file":"lib/RDF/Trine/Parser/RDFPatch.pm"},"RDF::Trine::Parser::RDFPatch::Op":{"version":"1.014","file":"lib/RDF/Trine/Parser/RDFPatch.pm"},"RDF::Trine::Exporter::RDFPatch":{"version":"1.014","file":"lib/RDF/Trine/Exporter/RDFPatch.pm"},"RDF::Trine::Parser::NQuads":{"version":"1.014","file":"lib/RDF/Trine/Parser/NQuads.pm"},"RDF::Trine::Store::Hexastore":{"file":"lib/RDF/Trine/Store/Hexastore.pm","version":"1.014"},"RDF::Trine::Iterator::Graph":{"file":"lib/RDF/Trine/Iterator/Graph.pm","version":"1.014"},"RDF::Trine::Parser::Turtle::Constants":{"file":"lib/RDF/Trine/Parser/Turtle/Constants.pm","version":"1.014"},"RDF::Trine::Parser::LineProtocol":{"version":"1.014","file":"lib/RDF/Trine/Parser/LineProtocol.pm"},"RDF::Trine::Serializer":{"version":"1.014","file":"lib/RDF/Trine/Serializer.pm"},"RDF::Trine::Iterator::Graph::Materialized":{"file":"lib/RDF/Trine/Iterator/Graph/Materialized.pm","version":"1.014"},"RDF::Trine::Serializer::RDFPatch":{"version":"1.014","file":"lib/RDF/Trine/Serializer/RDFPatch.pm"},"RDF::Trine::Model::StatementFilter":{"version":"1.014","file":"lib/RDF/Trine/Model/StatementFilter.pm"},"RDF::Trine::Parser::Redland::RDFa":{"file":"lib/RDF/Trine/Parser/Redland.pm","version":"1.014"},"RDF::Trine::Statement::Quad":{"file":"lib/RDF/Trine/Statement/Quad.pm","version":"1.014"},"RDF::Trine::Store::DBI::mysql":{"file":"lib/RDF/Trine/Store/DBI/mysql.pm","version":"1.014"},"RDF::Trine::Parser::RDFa":{"file":"lib/RDF/Trine/Parser/RDFa.pm","version":"1.014"},"Test::RDF::Trine::Store":{"file":"lib/Test/RDF/Trine/Store.pm","version":"1.014"},"RDF::Trine::Error::UnimplementedError":{"version":"1.014","file":"lib/RDF/Trine/Error.pm"},"RDF::Trine::Iterator::JSONHandler":{"file":"lib/RDF/Trine/Iterator/JSONHandler.pm","version":"1.014"},"RDF::Trine::Parser::Redland::NTriples":{"version":"1.014","file":"lib/RDF/Trine/Parser/Redland.pm"},"RDF::Trine::Iterator::Boolean":{"version":"1.014","file":"lib/RDF/Trine/Iterator/Boolean.pm"},"RDF::Trine::Statement":{"file":"lib/RDF/Trine/Statement.pm","version":"1.014"},"RDF::Trine::Error":{"version":"1.014","file":"lib/RDF/Trine/Error.pm"},"RDF::Trine::Serializer::StringSink":{"file":"lib/RDF/Trine/Serializer.pm","version":"1.014"},"RDF::Trine::Error::ParserError":{"file":"lib/RDF/Trine/Error.pm","version":"1.014"},"RDF::Trine::Store::Memory":{"file":"lib/RDF/Trine/Store/Memory.pm","version":"1.014"},"RDF::Trine::Store::DBI::Pg":{"file":"lib/RDF/Trine/Store/DBI/Pg.pm","version":"1.014"},"RDF::Trine::Store":{"file":"lib/RDF/Trine/Store.pm","version":"1.014"},"RDF::Trine::Serializer::RDFJSON":{"version":"1.014","file":"lib/RDF/Trine/Serializer/RDFJSON.pm"},"RDF::Trine::VariableBindings":{"version":"1.014","file":"lib/RDF/Trine/VariableBindings.pm"},"RDF::Trine::Exporter::CSV":{"file":"lib/RDF/Trine/Exporter/CSV.pm","version":"1.014"},"RDF::Trine::Iterator::SAXHandler":{"version":"1.014","file":"lib/RDF/Trine/Iterator/SAXHandler.pm"},"RDF::Trine::Node::Literal":{"file":"lib/RDF/Trine/Node/Literal.pm","version":"1.014"},"RDF::Trine::Parser":{"file":"lib/RDF/Trine/Parser.pm","version":"1.014"},"RDF::Trine::Parser::RDFJSON":{"version":"1.014","file":"lib/RDF/Trine/Parser/RDFJSON.pm"},"RDF::Trine::Serializer::TriG":{"version":"1.014","file":"lib/RDF/Trine/Serializer/TriG.pm"},"RDF::Trine::Error::SerializationError":{"version":"1.014","file":"lib/RDF/Trine/Error.pm"},"RDF::Trine::Error::CompilationError":{"file":"lib/RDF/Trine/Error.pm","version":"1.014"},"RDF::Trine::Error::ParserError::Positioned":{"file":"lib/RDF/Trine/Error.pm","version":"1.014"},"RDF::Trine::Store::DBI":{"version":"1.014","file":"lib/RDF/Trine/Store/DBI.pm"},"RDF::Trine::Node::Blank":{"file":"lib/RDF/Trine/Node/Blank.pm","version":"1.014"}},"target":"RDF::Trine"}